mb_annotation/__init__.py
mb_annotation/bounding_box.py
mb_annotation/florencefile.py
mb_annotation/molmo.py
mb_annotation/segsam2.py
mb_annotation/utils.py
mb_annotation/version.py
mb_annotation-1.0.63.dist-info/METADATA
mb_annotation-1.0.63.dist-info/WHEEL
mb_annotation-1.0.63.dist-info/top_level.txt
mb_annotation-1.0.63.dist-info/RECORD
