Metadata-Version: 2.1
Name: mb_annotation
Version: 1.0.63
Summary: Annotation tool for the MB project
Author: ['Malav Bateriwala']
Requires-Python: >=3.8
Requires-Dist: mb_base
